plane/__init__.py
plane/func.py
plane/pattern.py
plane/pipeline.py
plane/plane.py
plane/punctuation.py
plane-0.2.1.dist-info/LICENSE.txt
plane-0.2.1.dist-info/METADATA
plane-0.2.1.dist-info/WHEEL
plane-0.2.1.dist-info/top_level.txt
plane-0.2.1.dist-info/RECORD
