Metadata-Version: 2.1
Name: plane
Version: 0.2.1
Summary: A lib for text preprocessing
Home-page: https://github.com/kemingy/Plane
Author: Keming Yang
Author-email: kemingy94@gmail.com
License: MIT
Platform: UNKNOWN
Classifier: Topic :: Text Processing
Classifier: Programming Language :: Python :: 3.5
Classifier: Programming Language :: Python :: 3.6
Requires-Python: >=3
Provides-Extra: dev
Requires-Dist: pytest (>=6) ; extra == 'dev'
Requires-Dist: flake8 (>=3.8) ; extra == 'dev'
Requires-Dist: black (>=20.8b1) ; extra == 'dev'
Requires-Dist: isort (>=5.6) ; extra == 'dev'
Requires-Dist: autoflake (>=1.4) ; extra == 'dev'
